interactive_system_magic/__init__.py
interactive_system_magic-0.2.0.dist-info/LICENSES/MIT.txt
interactive_system_magic-0.2.0.dist-info/WHEEL
interactive_system_magic-0.2.0.dist-info/METADATA
interactive_system_magic-0.2.0.dist-info/RECORD
