Metadata-Version: 2.1
Name: interactive-system-magic
Version: 0.2.0
Summary: An IPython magic to run system commands interactively
Home-page: https://github.com/milliams/interactive-system-magic
License: MIT
Author: Matt Williams
Author-email: matt@milliams.com
Requires-Python: >=3.8,<4.0
Classifier: Framework :: IPython
Classifier: License :: OSI Approved :: MIT License
Classifier: Programming Language :: Python :: 3
Classifier: Programming Language :: Python :: 3.10
Classifier: Programming Language :: Python :: 3.8
Classifier: Programming Language :: Python :: 3.9
Requires-Dist: ipython (>=8.4.0,<9.0.0)
Requires-Dist: pexpect (>=4.6.0,<5.0.0)
Project-URL: Repository, https://github.com/milliams/interactive-system-magic
